pyfcf/__init__.py
pyfcf/basic.py
pyfcf/version.py
pyfcf-0.1.1.dist-info/METADATA
pyfcf-0.1.1.dist-info/WHEEL
pyfcf-0.1.1.dist-info/licenses/LICENSE
pyfcf-0.1.1.dist-info/RECORD
