Metadata-Version: 2.4
Name: pyfcf
Version: 0.1.1
Summary: Package to create standardized, publication quality matplotlib figures
Author-email: Katherine Rosenfeld <krosenf@gmail.com>
License-File: LICENSE
Classifier: License :: OSI Approved :: MIT License
Classifier: Operating System :: OS Independent
Classifier: Programming Language :: Python :: 3
Requires-Python: >=3.7
Requires-Dist: matplotlib
